[
  {
    "StapNummer": "0.5",
    "ValueMin25": "2.83",
    "ValueMin20": "3",
    "ValueMin10": "3.37",
    "Value0": "3.76",
    "ValuePlus10": "4.19",
    "ValuePlus20": "4.65",
    "ValuePlus25": "4.89"
  },
  {
    "StapNummer": "1",
    "ValueMin25": "3.15",
    "ValueMin20": "3.34",
    "ValueMin10": "3.75",
    "Value0": "4.19",
    "ValuePlus10": "4.66",
    "ValuePlus20": "5.17",
    "ValuePlus25": "5.44"
  },
  {
    "StapNummer": "1.5",
    "ValueMin25": "3.47",
    "ValueMin20": "3.68",
    "ValueMin10": "4.13",
    "Value0": "4.61",
    "ValuePlus10": "5.13",
    "ValuePlus20": "5.69",
    "ValuePlus25": "5.98"
  },
  {
    "StapNummer": "10",
    "ValueMin25": "7.15",
    "ValueMin20": "7.56",
    "ValueMin10": "8.42",
    "Value0": "9.36",
    "ValuePlus10": "10.38",
    "ValuePlus20": "11.47",
    "ValuePlus25": "12.06"
  },
  {
    "StapNummer": "10.5",
    "ValueMin25": "7.29",
    "ValueMin20": "7.71",
    "ValueMin10": "8.59",
    "Value0": "9.54",
    "ValuePlus10": "10.57",
    "ValuePlus20": "11.69",
    "ValuePlus25": "12.29"
  },
  {
    "StapNummer": "11",
    "ValueMin25": "7.43",
    "ValueMin20": "7.85",
    "ValueMin10": "8.75",
    "Value0": "9.72",
    "ValuePlus10": "10.77",
    "ValuePlus20": "11.91",
    "ValuePlus25": "12.52"
  },
  {
    "StapNummer": "11.5",
    "ValueMin25": "7.56",
    "ValueMin20": "7.99",
    "ValueMin10": "8.9",
    "Value0": "9.89",
    "ValuePlus10": "10.96",
    "ValuePlus20": "12.12",
    "ValuePlus25": "12.74"
  },
  {
    "StapNummer": "12",
    "ValueMin25": "7.69",
    "ValueMin20": "8.13",
    "ValueMin10": "9.05",
    "Value0": "10.06",
    "ValuePlus10": "11.15",
    "ValuePlus20": "12.33",
    "ValuePlus25": "12.96"
  },
  {
    "StapNummer": "12.5",
    "ValueMin25": "7.82",
    "ValueMin20": "8.26",
    "ValueMin10": "9.2",
    "Value0": "10.23",
    "ValuePlus10": "11.33",
    "ValuePlus20": "12.53",
    "ValuePlus25": "13.17"
  },
  {
    "StapNummer": "13",
    "ValueMin25": "7.95",
    "ValueMin20": "8.4",
    "ValueMin10": "9.35",
    "Value0": "10.39",
    "ValuePlus10": "11.52",
    "ValuePlus20": "12.74",
    "ValuePlus25": "13.38"
  },
  {
    "StapNummer": "13.5",
    "ValueMin25": "8.07",
    "ValueMin20": "8.52",
    "ValueMin10": "9.49",
    "Value0": "10.54",
    "ValuePlus10": "11.68",
    "ValuePlus20": "12.92",
    "ValuePlus25": "13.58"
  },
  {
    "StapNummer": "14",
    "ValueMin25": "8.18",
    "ValueMin20": "8.64",
    "ValueMin10": "9.62",
    "Value0": "10.69",
    "ValuePlus10": "11.85",
    "ValuePlus20": "13.11",
    "ValuePlus25": "13.77"
  },
  {
    "StapNummer": "14.5",
    "ValueMin25": "8.3",
    "ValueMin20": "8.77",
    "ValueMin10": "9.76",
    "Value0": "10.84",
    "ValuePlus10": "12.02",
    "ValuePlus20": "13.29",
    "ValuePlus25": "13.97"
  },
  {
    "StapNummer": "15",
    "ValueMin25": "8.42",
    "ValueMin20": "8.89",
    "ValueMin10": "9.89",
    "Value0": "10.99",
    "ValuePlus10": "12.18",
    "ValuePlus20": "13.48",
    "ValuePlus25": "14.16"
  },
  {
    "StapNummer": "2",
    "ValueMin25": "3.78",
    "ValueMin20": "4.01",
    "ValueMin10": "4.49",
    "Value0": "5.02",
    "ValuePlus10": "5.58",
    "ValuePlus20": "6.18",
    "ValuePlus25": "6.5"
  },
  {
    "StapNummer": "2.5",
    "ValueMin25": "4.09",
    "ValueMin20": "4.34",
    "ValueMin10": "4.86",
    "Value0": "5.42",
    "ValuePlus10": "6.02",
    "ValuePlus20": "6.68",
    "ValuePlus25": "7.02"
  },
  {
    "StapNummer": "3",
    "ValueMin25": "4.38",
    "ValueMin20": "4.64",
    "ValueMin10": "5.19",
    "Value0": "5.79",
    "ValuePlus10": "6.44",
    "ValuePlus20": "7.13",
    "ValuePlus25": "7.5"
  },
  {
    "StapNummer": "3.5",
    "ValueMin25": "4.66",
    "ValueMin20": "4.93",
    "ValueMin10": "5.52",
    "Value0": "6.15",
    "ValuePlus10": "6.83",
    "ValuePlus20": "7.57",
    "ValuePlus25": "7.96"
  },
  {
    "StapNummer": "4",
    "ValueMin25": "4.91",
    "ValueMin20": "5.2",
    "ValueMin10": "5.82",
    "Value0": "6.48",
    "ValuePlus10": "7.2",
    "ValuePlus20": "7.97",
    "ValuePlus25": "8.38"
  },
  {
    "StapNummer": "4.5",
    "ValueMin25": "5.16",
    "ValueMin20": "5.46",
    "ValueMin10": "6.1",
    "Value0": "6.8",
    "ValuePlus10": "7.55",
    "ValuePlus20": "8.36",
    "ValuePlus25": "8.79"
  },
  {
    "StapNummer": "5",
    "ValueMin25": "5.38",
    "ValueMin20": "5.7",
    "ValueMin10": "6.37",
    "Value0": "7.09",
    "ValuePlus10": "7.87",
    "ValuePlus20": "8.71",
    "ValuePlus25": "9.16"
  },
  {
    "StapNummer": "5.5",
    "ValueMin25": "5.6",
    "ValueMin20": "5.93",
    "ValueMin10": "6.62",
    "Value0": "7.37",
    "ValuePlus10": "8.18",
    "ValuePlus20": "9.05",
    "ValuePlus25": "9.51"
  },
  {
    "StapNummer": "6",
    "ValueMin25": "5.8",
    "ValueMin20": "6.14",
    "ValueMin10": "6.86",
    "Value0": "7.63",
    "ValuePlus10": "8.47",
    "ValuePlus20": "9.37",
    "ValuePlus25": "9.85"
  },
  {
    "StapNummer": "6.5",
    "ValueMin25": "6",
    "ValueMin20": "6.35",
    "ValueMin10": "7.08",
    "Value0": "7.88",
    "ValuePlus10": "8.74",
    "ValuePlus20": "9.67",
    "ValuePlus25": "10.16"
  },
  {
    "StapNummer": "7",
    "ValueMin25": "6.18",
    "ValueMin20": "6.53",
    "ValueMin10": "7.29",
    "Value0": "8.11",
    "ValuePlus10": "9",
    "ValuePlus20": "9.95",
    "ValuePlus25": "10.46"
  },
  {
    "StapNummer": "7.5",
    "ValueMin25": "6.36",
    "ValueMin20": "6.72",
    "ValueMin10": "7.5",
    "Value0": "8.34",
    "ValuePlus10": "9.25",
    "ValuePlus20": "10.23",
    "ValuePlus25": "10.75"
  },
  {
    "StapNummer": "8",
    "ValueMin25": "6.53",
    "ValueMin20": "6.9",
    "ValueMin10": "7.7",
    "Value0": "8.56",
    "ValuePlus10": "9.49",
    "ValuePlus20": "10.5",
    "ValuePlus25": "11.03"
  },
  {
    "StapNummer": "8.5",
    "ValueMin25": "6.69",
    "ValueMin20": "7.08",
    "ValueMin10": "7.89",
    "Value0": "8.77",
    "ValuePlus10": "9.72",
    "ValuePlus20": "10.75",
    "ValuePlus25": "11.3"
  },
  {
    "StapNummer": "9",
    "ValueMin25": "6.85",
    "ValueMin20": "7.24",
    "ValueMin10": "8.07",
    "Value0": "8.97",
    "ValuePlus10": "9.95",
    "ValuePlus20": "11",
    "ValuePlus25": "11.56"
  },
  {
    "StapNummer": "9.5",
    "ValueMin25": "7",
    "ValueMin20": "7.4",
    "ValueMin10": "8.25",
    "Value0": "9.17",
    "ValuePlus10": "10.17",
    "ValuePlus20": "11.24",
    "ValuePlus25": "11.81"
  }
]